sms_gateway_sdk/__init__.py
sms_gateway_sdk/client.py
sms_gateway_sdk/exceptions.py
sms_gateway_sdk-0.1.0.dist-info/LICENSE
sms_gateway_sdk-0.1.0.dist-info/METADATA
sms_gateway_sdk-0.1.0.dist-info/WHEEL
sms_gateway_sdk-0.1.0.dist-info/top_level.txt
sms_gateway_sdk-0.1.0.dist-info/RECORD
